MANIFEST.in
README.md
setup.py
braga/__init__.py
braga/aspect.py
braga/assemblage.py
braga/component.py
braga/entity.py
braga/system.py
braga/world.py
braga.egg-info/PKG-INFO
braga.egg-info/SOURCES.txt
braga.egg-info/dependency_links.txt
braga.egg-info/not-zip-safe
braga.egg-info/top_level.txt