Metadata-Version: 1.0
Name: braga
Version: 0.5.7
Summary: Entity-Component system
Home-page: http://github.com/astrosilverio/braga
Author: astrosilverio
Author-email: astrosilverio@gmail.com
License: MIT
Platform: UNKNOWN
